lidb/__init__.py
lidb/database.py
lidb/dataset.py
lidb/decorator.py
lidb/init.py
lidb/parse.py
lidb/table.py
lidb/qdf/__init__.py
lidb/qdf/errors.py
lidb/qdf/expr.py
lidb/qdf/lazy.py
lidb/qdf/lazy2.py
lidb/qdf/qdf.py
lidb/qdf/udf/__init__.py
lidb/qdf/udf/base_udf.py
lidb/qdf/udf/cs_udf.py
lidb/qdf/udf/d_udf.py
lidb/qdf/udf/itd_udf.py
lidb/qdf/udf/ts_udf.py
lidb/svc/__init__.py
lidb/svc/data.py
lidb-2.1.8.dist-info/METADATA
lidb-2.1.8.dist-info/WHEEL
lidb-2.1.8.dist-info/top_level.txt
lidb-2.1.8.dist-info/RECORD
