Metadata-Version: 2.4
Name: lidb
Version: 2.1.8
Summary: Light database for quantor
Requires-Python: >=3.12
Requires-Dist: dynaconf>=3.2.11
Requires-Dist: polars>=1.31.0
Requires-Dist: sqlparse>=0.5.3
Requires-Dist: logair>=1.0.8
Requires-Dist: clickhouse-df>=0.1.5
Requires-Dist: connectorx>=0.4.3
Requires-Dist: pymysql>=1.1.2
Requires-Dist: xcals>=0.1.5
Requires-Dist: ygo>=1.2.16
Requires-Dist: lark>=1.3.1
Requires-Dist: numpy>=2.3.1
Requires-Dist: tqdm>=4.67.1
Requires-Dist: varname>=0.15.1
